mp_pyrho-0.5.1.dist-info/licenses/AUTHORS.md
mp_pyrho-0.5.1.dist-info/licenses/LICENSE
pyrho/__init__.py
pyrho/charge_density.py
pyrho/pgrid.py
pyrho/utils.py
pyrho/vis/__init__.py
pyrho/vis/scatter.py
mp_pyrho-0.5.1.dist-info/METADATA
mp_pyrho-0.5.1.dist-info/WHEEL
mp_pyrho-0.5.1.dist-info/top_level.txt
mp_pyrho-0.5.1.dist-info/RECORD
